FamousCipherAlgorithms/ADFGVX.py
FamousCipherAlgorithms/Affine.py
FamousCipherAlgorithms/Columnar.py
FamousCipherAlgorithms/Hill.py
FamousCipherAlgorithms/OneTimePad.py
FamousCipherAlgorithms/Permutation.py
FamousCipherAlgorithms/Playfair.py
FamousCipherAlgorithms/Polybius.py
FamousCipherAlgorithms/RailFence.py
FamousCipherAlgorithms/Shift.py
FamousCipherAlgorithms/Vigenere.py
FamousCipherAlgorithms/__init__.py
famouscipheralgorithms-0.1.4.dist-info/METADATA
famouscipheralgorithms-0.1.4.dist-info/WHEEL
famouscipheralgorithms-0.1.4.dist-info/licenses/LICENSE
famouscipheralgorithms-0.1.4.dist-info/RECORD
