Metadata-Version: 2.1
Name: FamousCipherAlgorithms
Version: 0.1.4
Summary: FamousCipherAlgorithms is a Python package for implementing a variety of cryptographic ciphers and encryption methods, designed to provide secure and reliable data protection.
Project-URL: Repository, https://github.com/MobinNesari81/Famous-Cipher-Algorithms
Project-URL: Documentation, https://famous-cipher-algorithm.readthedocs.io/en/latest/index.html
Author-email: Mobin Nesari <mobinnesari81@gmail.com>, Mohammad Mehdi Begmaz <mohammadmehdi.begmaz@gmail.com>
Maintainer-email: Mobin Nesari <mobinnesari@gmail.com>, Mohammad Mehdi Begmaz <mohammadmehdi.begmaz@gmail.com>
License-File: LICENSE
Keywords: Algorithms,Cipher,Cryptography,Decrypt,Encrypt
Classifier: License :: OSI Approved :: MIT License
Classifier: Operating System :: OS Independent
Classifier: Programming Language :: Python :: 3
Requires-Python: >=3.9
Requires-Dist: numpy<=1.21.5
